{
  "project_info": {
    "project_number": "917630960160",
    "project_id": "carhub-utfpr-01",
    "storage_bucket": "carhub-utfpr-01.firebasestorage.app"
  },
  "client": [
    {
      "client_info": {
        "mobilesdk_app_id": "1:917630960160:android:0e6d675fef354df1183245",
        "android_client_info": {
          "package_name": "com.example.utfpr.carhub"
        }
      },
      "oauth_client": [],
      "api_key": [
        {
          "current_key": "KEY_DO_MOODLE"
        }
      ],
      "services": {
        "appinvite_service": {
          "other_platform_oauth_client": []
        }
      }
    }
  ],
  "configuration_version": "1"
}
